project_version_manager-0.1.1.dist-info/licenses/LICENSE
pvm/__init__.py
pvm/__main__.py
pvm/config.py
pvm/exceptions.py
pvm/hooks.py
pvm/py.typed
pvm/pyproject.py
pvm/version.py
pvm/changelog/__init__.py
pvm/changelog/generator.py
pvm/changelog/utils.py
pvm/cli/__init__.py
pvm/cli/bump.py
pvm/cli/changelog.py
pvm/cli/show/__init__.py
pvm/cli/show/current.py
pvm/cli/show/next.py
pvm/git/__init__.py
pvm/git/comparison_links.py
pvm/git/parser.py
pvm/git/repo.py
pvm/git/utils.py
project_version_manager-0.1.1.dist-info/METADATA
project_version_manager-0.1.1.dist-info/WHEEL
project_version_manager-0.1.1.dist-info/entry_points.txt
project_version_manager-0.1.1.dist-info/top_level.txt
project_version_manager-0.1.1.dist-info/RECORD
