Metadata-Version: 2.4
Name: project-version-manager
Version: 0.1.1
Summary: Project Version Manager. A tool for bumping python project versions following SemVer 2.0.0
Author-email: Malvin Ndip <23006212+DazzyMlv@users.noreply.github.com>
License: MIT
Project-URL: Homepage, https://github.com/dazzymlv/pvm
Project-URL: source, https://github.com/dazzymlv/pvm.git
Project-URL: changelog, https://github.com/dazzymlv/pvm/CHANGELOG.md
Project-URL: issues, https://github.com/dazzymlv/pvm/issues
Project-URL: documentation, https://github.com/dazzymlv/pvm/README.md
Keywords: bump,bumping,changelog,manager,version
Classifier: Development Status :: 3 - Alpha
Classifier: Environment :: Console
Classifier: Intended Audience :: Developers
Classifier: Intended Audience :: Information Technology
Classifier: Intended Audience :: System Administrators
Classifier: License :: OSI Approved :: MIT License
Classifier: Natural Language :: English
Classifier: Operating System :: OS Independent
Classifier: Programming Language :: Python
Classifier: Programming Language :: Python :: 3
Classifier: Programming Language :: Python :: 3 :: Only
Classifier: Programming Language :: Python :: 3.11
Classifier: Programming Language :: Python :: 3.12
Classifier: Programming Language :: Python :: 3.13
Classifier: Topic :: Software Development
Classifier: Topic :: Software Development :: Build Tools
Classifier: Topic :: Software Development :: Libraries
Classifier: Topic :: Software Development :: Libraries :: Python Modules
Classifier: Topic :: Software Development :: Version Control
Classifier: Topic :: Software Development :: Version Control :: Git
Classifier: Topic :: System :: Archiving :: Packaging
Classifier: Topic :: System :: Installation/Setup
Classifier: Topic :: System :: Software Distribution
Classifier: Typing :: Typed
Requires-Python: >=3.11
License-File: LICENSE
Requires-Dist: configupdater>=3.2
Requires-Dist: gitpython>=3.1.44
Requires-Dist: jinja2>=3.1.6
Requires-Dist: packaging>=25.0
Requires-Dist: ruamel-yaml>=0.18.10
Requires-Dist: semver>=3.0.0
Requires-Dist: tomlkit>=0.13.2
Requires-Dist: typer>=0.15.3
Dynamic: license-file
